cryogrid_pytools/__init__.py
cryogrid_pytools/analyze.py
cryogrid_pytools/excel_config.py
cryogrid_pytools/forcing.py
cryogrid_pytools/matlab_helpers.py
cryogrid_pytools/outputs.py
cryogrid_pytools/spatial_clusters.py
cryogrid_pytools/utils.py
cryogrid_pytools/data/__init__.py
cryogrid_pytools/data/from_earth_engine.py
cryogrid_pytools/data/from_planetary_computer.py
cryogrid_pytools/data/shapefiles.py
cryogrid_pytools/data/utils.py
cryogrid_pytools/viz/__init__.py
cryogrid_pytools/viz/maps.py
cryogrid_pytools/viz/profiles.py
cryogrid_pytools/xr_raster_vector/__init__.py
cryogrid_pytools/xr_raster_vector/accessors.py
cryogrid_pytools/xr_raster_vector/conversion.py
cryogrid_pytools/xr_raster_vector/raster.py
cryogrid_pytools/xr_raster_vector/utils.py
cryogrid_pytools/xr_raster_vector/vector.py
cryogrid_pytools-0.3.20.dist-info/METADATA
cryogrid_pytools-0.3.20.dist-info/WHEEL
cryogrid_pytools-0.3.20.dist-info/licenses/LICENSE
cryogrid_pytools-0.3.20.dist-info/RECORD
