Metadata-Version: 2.4
Name: cryogrid_pytools
Version: 0.3.20
Summary: Tools to read in CryoGrid MATLAB data to Python and create forcing data
Project-URL: Homepage, https://github.com/lukegre/CryoGrid-pyTools
Project-URL: CryoGrid, https://github.com/CryoGrid
Project-URL: Documentation, https://lukegre.github.io/CryoGrid-pyTools/
Maintainer-email: Luke Gregor <lukegre@gmail.com>
License-Expression: MIT
License-File: LICENSE
Classifier: Development Status :: 3 - Alpha
Classifier: Intended Audience :: Education
Classifier: License :: OSI Approved :: MIT License
Classifier: Programming Language :: Python :: 3
Classifier: Programming Language :: Python :: 3 :: Only
Classifier: Programming Language :: Python :: 3.9
Classifier: Programming Language :: Python :: 3.10
Classifier: Programming Language :: Python :: 3.11
Classifier: Programming Language :: Python :: 3.12
Classifier: Programming Language :: Python :: 3.13
Classifier: Topic :: Scientific/Engineering :: Hydrology
Requires-Python: >=3.11
Requires-Dist: dask[array,diagnostics]>=2024
Requires-Dist: joblib
Requires-Dist: loguru
Requires-Dist: matplotlib
Requires-Dist: munch
Requires-Dist: numpy>=2.0
Requires-Dist: openpyxl
Requires-Dist: pandas>=2
Requires-Dist: pip>=24
Requires-Dist: scipy>=1.13.1
Requires-Dist: xarray>=2024
Provides-Extra: data
Requires-Dist: bottleneck>=1.4.2; extra == 'data'
Requires-Dist: earthaccess>=0.11.0; extra == 'data'
Requires-Dist: earthengine-api>=1.5.9; extra == 'data'
Requires-Dist: era5-downloader>=0.1.4; extra == 'data'
Requires-Dist: geopandas>=1.0.1; extra == 'data'
Requires-Dist: ipywidgets>=8.1.5; extra == 'data'
Requires-Dist: memoization>=0.4.0; extra == 'data'
Requires-Dist: planetary-computer>=1.0.0; extra == 'data'
Requires-Dist: pooch>=1.8.2; extra == 'data'
Requires-Dist: pyarrow>=19.0.1; extra == 'data'
Requires-Dist: pystac-client>=0.8.3; extra == 'data'
Requires-Dist: pyzenodo3>=1.0.2; extra == 'data'
Requires-Dist: rioxarray>=0.15.0; extra == 'data'
Requires-Dist: scikit-image>=0.24.0; extra == 'data'
Requires-Dist: setuptools>=78.1.0; extra == 'data'
Requires-Dist: stackstac>=0.5.1; extra == 'data'
Requires-Dist: wxee>=0.4.2; extra == 'data'
Requires-Dist: zarr>3; extra == 'data'
Provides-Extra: dev
Requires-Dist: ipykernel>=6.29.5; extra == 'dev'
Provides-Extra: docs
Requires-Dist: mkdocs-material>=8.2.10; extra == 'docs'
Requires-Dist: mkdocs-rtd-dropdown>=1.0.2; extra == 'docs'
Requires-Dist: mkdocs>=1.5.0; extra == 'docs'
Requires-Dist: mkdocstrings-python>=1.7.0; extra == 'docs'
Requires-Dist: mkdocstrings>=0.24.0; extra == 'docs'
Requires-Dist: pymdown-extensions>=10.14.1; extra == 'docs'
Provides-Extra: viz
Requires-Dist: folium>=0.19.5; extra == 'viz'
Requires-Dist: geopandas>=1.0.1; extra == 'viz'
Requires-Dist: mapclassify>=2.8.1; extra == 'viz'
Requires-Dist: matplotlib>=3.9.4; extra == 'viz'
Requires-Dist: rioxarray>=0.15.0; extra == 'viz'
Requires-Dist: scikit-image>=0.24.0; extra == 'viz'
